gammaloop-0.3.3.dist-info/METADATA
gammaloop-0.3.3.dist-info/WHEEL
gammaloop-0.3.3.dist-info/entry_points.txt
gammaloop-0.3.3.dist-info/licenses/LICENSE.md
gammaloop/misc/__init__.py
gammaloop/misc/common.py
gammaloop/misc/utils.py
gammaloop/interface/debug_display.py
gammaloop/interface/__init__.py
gammaloop/interface/gammaloop_interface.py
gammaloop/base_objects/graph.py
gammaloop/base_objects/__init__.py
gammaloop/base_objects/model.py
gammaloop/base_objects/process.py
gammaloop/base_objects/param_card.py
gammaloop/.DS_Store
gammaloop/pytest.ini
gammaloop/requirements.txt
gammaloop/bin/gammaloop
gammaloop/bin/__init__.py
gammaloop/bin/build_dependencies.sh
gammaloop/bin/patch_symbolica.py
gammaloop/run_python_tests.sh
gammaloop/exporters/__init__.py
gammaloop/exporters/exporters.py
gammaloop/tests/unit/test_misc.py
gammaloop/tests/unit/__init__.py
gammaloop/tests/unit/test_commands.py
gammaloop/tests/unit/test_inspect.py
gammaloop/tests/unit/test_process_generation.py
gammaloop/tests/unit/test_rust.py
gammaloop/tests/unit/test_objects.py
gammaloop/tests/unit/test_graph_functions.py
gammaloop/tests/conftest.py
gammaloop/tests/integration/test_integral.py
gammaloop/tests/integration/__init__.py
gammaloop/tests/test_data/models/loop_sm/write_param_card.py
gammaloop/tests/test_data/models/loop_sm/restrict_ckm.dat
gammaloop/tests/test_data/models/loop_sm/couplings.py
gammaloop/tests/test_data/models/loop_sm/lorentz.py
gammaloop/tests/test_data/models/loop_sm/restrict_parallel_test.dat
gammaloop/tests/test_data/models/loop_sm/__init__.py
gammaloop/tests/test_data/models/loop_sm/CT_couplings.py
gammaloop/tests/test_data/models/loop_sm/particles.py
gammaloop/tests/test_data/models/loop_sm/restrict_test.dat
gammaloop/tests/test_data/models/loop_sm/object_library.py
gammaloop/tests/test_data/models/loop_sm/restrict_default.dat
gammaloop/tests/test_data/models/loop_sm/restrict_zeromass_ckm.dat
gammaloop/tests/test_data/models/loop_sm/restrict_no_b_mass.dat
gammaloop/tests/test_data/models/loop_sm/restrict_lepton_masses.dat
gammaloop/tests/test_data/models/loop_sm/function_library.py
gammaloop-0.3.3.dist-info/RECORD
