Metadata-Version: 2.4
Name: gammaloop
Version: 0.3.3
Classifier: Development Status :: 3 - Alpha
Classifier: Programming Language :: Rust
Classifier: Topic :: Scientific/Engineering :: Physics
Requires-Dist: pyyaml>=6.0.1
Requires-Dist: pymupdf>=1.23.4
Requires-Dist: pydot>=3.0.1
License-File: LICENSE.md
License-File: LICENSE.md
Summary: Gammaloop computes differential cross-sections using Local Unitarity
Keywords: physics,collider,cross-section,perturbative,loop
Author: Valentin Hirschi <valentin.hirschi@gmail.com>
Author-email: Valentin Hirschi <valentin.hirschi@gmail.com>, Mathijs Fraaije <mathijsfraaije@gmail.com>, Lucien Huber <mail@lcnbr.ch>
Requires-Python: >=3.7
Project-URL: homepage, https://alphaloop.ch
Project-URL: repository, https://github.com/alphal00p/gammaloop
